qax/__init__.py
qax/common/__init__.py
qax/common/type_utils.py
qax/common/utils.py
qax/constants.py
qax/implicit/__init__.py
qax/implicit/implicit_array.py
qax/implicit/implicit_utils.py
qax/primitives.py
qax/symbols.py
qax/utils.py
qax-0.4.1.dist-info/LICENSE
qax-0.4.1.dist-info/METADATA
qax-0.4.1.dist-info/WHEEL
qax-0.4.1.dist-info/RECORD
