Metadata-Version: 2.1
Name: qax
Version: 0.4.1
Summary: A JAX transform for writing things which pretend to be tensors
License: MIT
Author: Davis Yoshida
Author-email: dyoshida@ttic.edu
Requires-Python: >=3.10,<4.0
Classifier: License :: OSI Approved :: MIT License
Classifier: Programming Language :: Python :: 3
Classifier: Programming Language :: Python :: 3.10
Classifier: Programming Language :: Python :: 3.11
Classifier: Programming Language :: Python :: 3.12
Classifier: Programming Language :: Python :: 3.13
Requires-Dist: jax (>=0.4.24,<0.5.0)
Requires-Dist: jaxlib (>=0.4.24,<0.5.0)
Requires-Dist: optax (>=0.1.5,<0.2.0)
Requires-Dist: plum-dispatch (>=2.1.0,<3.0.0)
